cs/app/playon.py
cs.app.playon-20241007.dist-info/METADATA
cs.app.playon-20241007.dist-info/WHEEL
cs.app.playon-20241007.dist-info/entry_points.txt
cs.app.playon-20241007.dist-info/top_level.txt
cs.app.playon-20241007.dist-info/RECORD
