Metadata-Version: 2.1
Name: cs.app.playon
Version: 20241007
Summary: PlayOn facilities, primarily access to the download API. Includes a nice command line tool.
Author-email: Cameron Simpson <cs@cskk.id.au>
License: GNU General Public License v3 or later (GPLv3+)
Project-URL: Monorepo Hg/Mercurial Mirror, https://hg.sr.ht/~cameron-simpson/css
Project-URL: Monorepo Git Mirror, https://github.com/cameron-simpson/css
Project-URL: MonoRepo Commits, https://bitbucket.org/cameron_simpson/css/commits/branch/main
Project-URL: Source, https://github.com/cameron-simpson/css/blob/main/lib/python/cs/app/playon.py
Keywords: python3
Classifier: Development Status :: 5 - Production/Stable
Classifier: Environment :: Console
Classifier: Programming Language :: Python
Classifier: Programming Language :: Python :: 3
Classifier: Topic :: Utilities
Classifier: Intended Audience :: Developers
Classifier: Operating System :: OS Independent
Classifier: License :: OSI Approved :: GNU General Public License v3 or later (GPLv3+)
Requires-Dist: cs.cmdutils >=20241007
Requires-Dist: cs.context >=20240630
Requires-Dist: cs.deco >=20241007
Requires-Dist: cs.fileutils >=20210731
Requires-Dist: cs.fstags >=20241005
Requires-Dist: cs.lex >=20240630
Requires-Dist: cs.logutils >=20241007
Requires-Dist: cs.mediainfo >=20240519
Requires-Dist: cs.pfx >=20210731
Requires-Dist: cs.progress >=20240412
Requires-Dist: cs.resources >=20241005
Requires-Dist: cs.result >=20240630
Requires-Dist: cs.service-api >=20241007
Requires-Dist: cs.sqltags >=20240723
Requires-Dist: cs.tagset >=20241005
Requires-Dist: cs.threads >=20241005
Requires-Dist: cs.units
Requires-Dist: cs.upd >=20240630
Requires-Dist: icontract
Requires-Dist: requests
Requires-Dist: typeguard
